yggdrasil_rapidjson.so
yggdrasil_python_rapidjson-1.21.0.1.dist-info/METADATA
yggdrasil_python_rapidjson-1.21.0.1.dist-info/WHEEL
yggdrasil_python_rapidjson-1.21.0.1.dist-info/RECORD
yggdrasil_python_rapidjson-1.21.0.1.dist-info/licenses/LICENSE
