Metadata-Version: 2.2
Name: yggdrasil-python-rapidjson
Version: 1.21.0.1
Summary: Version of rapidjson Python wrapper with extended support for yggdrasil
Keywords: yggdrasil,json,jsonc,rapidjson
Author-Email: Meagan Lang <langmm.astro@gmail.com>
Maintainer-Email: Meagan Lang <langmm.astro@gmail.com>
License: python-rapidjson is licensed under the MIT license.
Classifier: Development Status :: 5 - Production/Stable
Classifier: Intended Audience :: Developers
Classifier: License :: OSI Approved :: MIT License
Classifier: Programming Language :: C++
Classifier: Programming Language :: Python :: 3 :: Only
Classifier: Programming Language :: Python :: 3
Classifier: Programming Language :: Python :: 3.9
Classifier: Programming Language :: Python :: 3.10
Classifier: Programming Language :: Python :: 3.11
Classifier: Programming Language :: Python :: 3.12
Classifier: Programming Language :: Python :: 3.13
Classifier: Programming Language :: Python
Project-URL: Repository, https://github.com/cropsinsilico/yggdrasil-python-rapidjson
Requires-Python: >=3.9
Requires-Dist: numpy
